{"data":{"contentfulAbout":{"name":"Charlie Pan","roles":["Full-Stack Web Developer"],"socialLinks":[{"id":"28e45daf-b9d6-581d-b9c8-fcd2cc9f4a90","url":"https://github.com/charliepan","name":"Github","fontAwesomeIcon":"github"},{"id":"4efbd1cb-e584-5175-a060-3499f2db853b","url":"https://hsinchihpan.typeform.com/to/yA4YOD","name":"Contact me","fontAwesomeIcon":"envelope"},{"id":"bf034aa6-4c3a-552e-8009-ffb424a2baa8","url":"https://twitter.com/CharliePan14","name":"Twitter","fontAwesomeIcon":"twitter"},{"id":"b6a8d746-1386-5bbe-85d3-64f7856b29b9","url":"https://www.linkedin.com/in/charlie-pan/","name":"Linkedin","fontAwesomeIcon":"linkedin"}]},"site":{"siteMetadata":{"deterministicBehaviour":false}}}}